{
    "configurations": [
        {
            "name": "Win32",
            "includePath": [
                "C:\\Users\\fadanner\\AppData\\Local\\Arduino15\\packages\\esp8266\\tools\\**",
                "C:\\Users\\fadanner\\AppData\\Local\\Arduino15\\packages\\esp8266\\hardware\\esp8266\\2.7.1\\**",
                "C:\\Program Files (x86)\\Arduino\\hardware\\**",
                "C:\\Users\\fadanner\\AppData\\Local\\Arduino15\\packages\\esp32\\tools\\**",
                "C:\\Users\\fadanner\\AppData\\Local\\Arduino15\\packages\\esp32\\hardware\\esp32\\1.0.4\\**",
                "${workspaceFolder}/**",
                "${env:UserProfile}\\Documents\\Arduino\\libraries/**",
                "C:\\Program Files (x86)\\Arduino\\libraries\\**",
                "C:\\Program Files (x86)\\Arduino\\hardware\\tools\\avr\\avr\\include\\avr\\**"
            ],
            "defines": [
                "_DEBUG",
                "UNICODE",
                "_UNICODE"
            ],
            "intelliSenseMode": "msvc-x64",
            "forcedInclude": []
        }
    ],
    "version": 4
}